lame_ctypes/__init__.py
lame_ctypes/_dll.py
lame_ctypes/_stdarg_ctypes.py
lame_ctypes/lame_ctypes.py
lame_ctypes-0.1.3.dist-info/WHEEL
lame_ctypes-0.1.3.dist-info/METADATA
lame_ctypes-0.1.3.dist-info/RECORD
